{
  "balance_usd": 1000.0037766104839,
  "positions": {
    "BTCUSDT": {
      "symbol": "BTCUSDT",
      "side": "buy",
      "entry_price": 80337.4,
      "notional_usd": 15,
      "qty": 0.00018671253986312728,
      "opened_at": "2026-05-09T11:21:51.638739Z"
    },
    "ETHUSDT": {
      "symbol": "ETHUSDT",
      "side": "buy",
      "entry_price": 2313.89,
      "notional_usd": 15,
      "qty": 0.006482589924326567,
      "opened_at": "2026-05-09T11:21:52.97918Z"
    }
  },
  "trades": [
    {
      "symbol": "BTCUSDT",
      "side": "buy",
      "entry_price": 80284.4,
      "exit_price": 80325.8,
      "notional_usd": 15,
      "qty": 0.00018683579873549533,
      "pnl_usd": 0.007735002067651138,
      "reason": "max_hold",
      "opened_at": "2026-05-09T03:43:46.147535Z",
      "closed_at": "2026-05-09T03:46:47.191435Z"
    },
    {
      "symbol": "BTCUSDT",
      "side": "buy",
      "entry_price": 80325.8,
      "exit_price": 80311.6,
      "notional_usd": 15,
      "qty": 0.0001867395033725154,
      "pnl_usd": -0.0026517009478891755,
      "reason": "max_hold",
      "opened_at": "2026-05-09T03:46:49.149727Z",
      "closed_at": "2026-05-09T03:50:17.218Z"
    },
    {
      "symbol": "BTCUSDT",
      "side": "buy",
      "entry_price": 80311.6,
      "exit_price": 80311.5,
      "notional_usd": 15,
      "qty": 0.00018677252103058584,
      "pnl_usd": -0.000018677252104145744,
      "reason": "max_hold",
      "opened_at": "2026-05-09T03:50:19.732721Z",
      "closed_at": "2026-05-09T03:53:47.185813Z"
    },
    {
      "symbol": "BTCUSDT",
      "side": "buy",
      "entry_price": 80311.5,
      "exit_price": 80355.1,
      "notional_usd": 15,
      "qty": 0.00018677275359070617,
      "pnl_usd": 0.008143292056555876,
      "reason": "max_hold",
      "opened_at": "2026-05-09T03:53:49.251938Z",
      "closed_at": "2026-05-09T03:56:52.401411Z"
    },
    {
      "symbol": "ETHUSDT",
      "side": "buy",
      "entry_price": 2314.99,
      "exit_price": 2314.74,
      "notional_usd": 15,
      "qty": 0.006479509630711149,
      "pnl_usd": -0.0016198774076777872,
      "reason": "max_hold",
      "opened_at": "2026-05-09T03:55:05.852982Z",
      "closed_at": "2026-05-09T03:58:33.390168Z"
    },
    {
      "symbol": "BTCUSDT",
      "side": "buy",
      "entry_price": 80355.1,
      "exit_price": 80347.6,
      "notional_usd": 15,
      "qty": 0.00018667141226879187,
      "pnl_usd": -0.001400035592015939,
      "reason": "max_hold",
      "opened_at": "2026-05-09T03:56:54.338785Z",
      "closed_at": "2026-05-09T04:00:01.266337Z"
    },
    {
      "symbol": "ETHUSDT",
      "side": "buy",
      "entry_price": 2314.74,
      "exit_price": 2315.12,
      "notional_usd": 15,
      "qty": 0.006480209440369113,
      "pnl_usd": 0.00246247958734097,
      "reason": "max_hold",
      "opened_at": "2026-05-09T03:58:35.334105Z",
      "closed_at": "2026-05-09T04:02:04.200271Z"
    },
    {
      "symbol": "BTCUSDT",
      "side": "buy",
      "entry_price": 80347.6,
      "exit_price": 80390,
      "notional_usd": 15,
      "qty": 0.000186688837003221,
      "pnl_usd": 0.007915606688935484,
      "reason": "max_hold",
      "opened_at": "2026-05-09T04:00:03.125611Z",
      "closed_at": "2026-05-09T04:03:08.330408Z"
    },
    {
      "symbol": "ETHUSDT",
      "side": "buy",
      "entry_price": 2315.12,
      "exit_price": 2317.99,
      "notional_usd": 15,
      "qty": 0.006479145789419123,
      "pnl_usd": 0.018595148415632177,
      "reason": "max_hold",
      "opened_at": "2026-05-09T04:02:06.125889Z",
      "closed_at": "2026-05-09T04:05:33.386479Z"
    },
    {
      "symbol": "BTCUSDT",
      "side": "buy",
      "entry_price": 80390,
      "exit_price": 80601.8,
      "notional_usd": 15,
      "qty": 0.00018659037193680805,
      "pnl_usd": 0.03951984077621649,
      "reason": "max_hold",
      "opened_at": "2026-05-09T04:03:10.783357Z",
      "closed_at": "2026-05-09T04:06:31.176582Z"
    },
    {
      "symbol": "ETHUSDT",
      "side": "buy",
      "entry_price": 2317.99,
      "exit_price": 2321.44,
      "notional_usd": 15,
      "qty": 0.006471123689058193,
      "pnl_usd": 0.02232537672725253,
      "reason": "max_hold",
      "opened_at": "2026-05-09T04:05:35.344119Z",
      "closed_at": "2026-05-09T04:09:03.374065Z"
    },
    {
      "symbol": "BTCUSDT",
      "side": "buy",
      "entry_price": 80601.8,
      "exit_price": 80581,
      "notional_usd": 15,
      "qty": 0.0001861000622814875,
      "pnl_usd": -0.0038708812954554818,
      "reason": "max_hold",
      "opened_at": "2026-05-09T04:06:33.681843Z",
      "closed_at": "2026-05-09T04:09:38.29795Z"
    },
    {
      "symbol": "ETHUSDT",
      "side": "buy",
      "entry_price": 2321.44,
      "exit_price": 2320.9,
      "notional_usd": 15,
      "qty": 0.006461506651044179,
      "pnl_usd": -0.0034892135915636216,
      "reason": "max_hold",
      "opened_at": "2026-05-09T04:09:05.240817Z",
      "closed_at": "2026-05-09T04:12:34.030427Z"
    },
    {
      "symbol": "BTCUSDT",
      "side": "buy",
      "entry_price": 80581,
      "exit_price": 80550.1,
      "notional_usd": 15,
      "qty": 0.00018614809942790484,
      "pnl_usd": -0.005751976272321176,
      "reason": "max_hold",
      "opened_at": "2026-05-09T04:09:40.290562Z",
      "closed_at": "2026-05-09T04:13:01.169956Z"
    },
    {
      "symbol": "ETHUSDT",
      "side": "buy",
      "entry_price": 2320.9,
      "exit_price": 2319.3,
      "notional_usd": 15,
      "qty": 0.006463010039208928,
      "pnl_usd": -0.010340816062733696,
      "reason": "max_hold",
      "opened_at": "2026-05-09T04:12:35.965919Z",
      "closed_at": "2026-05-09T04:16:03.323753Z"
    },
    {
      "symbol": "BTCUSDT",
      "side": "buy",
      "entry_price": 80550.1,
      "exit_price": 80504,
      "notional_usd": 15,
      "qty": 0.00018621950810737665,
      "pnl_usd": -0.008584719323751147,
      "reason": "max_hold",
      "opened_at": "2026-05-09T04:13:03.184666Z",
      "closed_at": "2026-05-09T04:16:08.29494Z"
    },
    {
      "symbol": "BTCUSDT",
      "side": "buy",
      "entry_price": 80504,
      "exit_price": 80475.3,
      "notional_usd": 15,
      "qty": 0.00018632614528470636,
      "pnl_usd": -0.005347560369670531,
      "reason": "max_hold",
      "opened_at": "2026-05-09T04:16:10.35035Z",
      "closed_at": "2026-05-09T04:19:31.162287Z"
    },
    {
      "symbol": "ETHUSDT",
      "side": "buy",
      "entry_price": 2319.3,
      "exit_price": 2317.12,
      "notional_usd": 15,
      "qty": 0.006467468632777131,
      "pnl_usd": -0.014099081619456028,
      "reason": "max_hold",
      "opened_at": "2026-05-09T04:16:05.174777Z",
      "closed_at": "2026-05-09T04:19:33.304715Z"
    },
    {
      "symbol": "BTCUSDT",
      "side": "buy",
      "entry_price": 80475.3,
      "exit_price": 80467.2,
      "notional_usd": 15,
      "qty": 0.00018639259499498602,
      "pnl_usd": -0.0015097800194604717,
      "reason": "max_hold",
      "opened_at": "2026-05-09T04:19:33.107383Z",
      "closed_at": "2026-05-09T04:22:38.300036Z"
    },
    {
      "symbol": "ETHUSDT",
      "side": "buy",
      "entry_price": 2317.12,
      "exit_price": 2317.25,
      "notional_usd": 15,
      "qty": 0.006473553376605441,
      "pnl_usd": 0.0008415619389594139,
      "reason": "max_hold",
      "opened_at": "2026-05-09T04:19:35.340301Z",
      "closed_at": "2026-05-09T04:23:04.204645Z"
    },
    {
      "symbol": "BTCUSDT",
      "side": "buy",
      "entry_price": 80467.2,
      "exit_price": 80455.1,
      "notional_usd": 15,
      "qty": 0.0001864113576712002,
      "pnl_usd": -0.002255577427819895,
      "reason": "max_hold",
      "opened_at": "2026-05-09T04:22:40.209959Z",
      "closed_at": "2026-05-09T04:26:01.197375Z"
    },
    {
      "symbol": "ETHUSDT",
      "side": "buy",
      "entry_price": 2317.25,
      "exit_price": 2316.24,
      "notional_usd": 15,
      "qty": 0.006473190203905492,
      "pnl_usd": -0.006537922105945959,
      "reason": "max_hold",
      "opened_at": "2026-05-09T04:23:06.143853Z",
      "closed_at": "2026-05-09T04:26:34.30553Z"
    },
    {
      "symbol": "BTCUSDT",
      "side": "buy",
      "entry_price": 80455.1,
      "exit_price": 80426.9,
      "notional_usd": 15,
      "qty": 0.00018643939290361952,
      "pnl_usd": -0.0052575908798842405,
      "reason": "max_hold",
      "opened_at": "2026-05-09T04:26:03.935932Z",
      "closed_at": "2026-05-09T04:29:08.362605Z"
    },
    {
      "symbol": "ETHUSDT",
      "side": "buy",
      "entry_price": 2316.24,
      "exit_price": 2315.71,
      "notional_usd": 15,
      "qty": 0.006476012848409492,
      "pnl_usd": -0.0034322868096553815,
      "reason": "max_hold",
      "opened_at": "2026-05-09T04:26:36.377715Z",
      "closed_at": "2026-05-09T04:30:03.420565Z"
    },
    {
      "symbol": "BTCUSDT",
      "side": "buy",
      "entry_price": 80426.9,
      "exit_price": 80410.9,
      "notional_usd": 15,
      "qty": 0.00018650476395335393,
      "pnl_usd": -0.002984076223253663,
      "reason": "max_hold",
      "opened_at": "2026-05-09T04:29:10.33172Z",
      "closed_at": "2026-05-09T04:38:47.063658Z"
    },
    {
      "symbol": "ETHUSDT",
      "side": "buy",
      "entry_price": 2315.71,
      "exit_price": 2314.09,
      "notional_usd": 15,
      "qty": 0.006477495023124657,
      "pnl_usd": -0.010493541937461237,
      "reason": "max_hold",
      "opened_at": "2026-05-09T04:30:05.325897Z",
      "closed_at": "2026-05-09T04:38:50.218664Z"
    },
    {
      "symbol": "ETHUSDT",
      "side": "buy",
      "entry_price": 2314.09,
      "exit_price": 2314.55,
      "notional_usd": 15,
      "qty": 0.006482029653124986,
      "pnl_usd": 0.002981733640437729,
      "reason": "max_hold",
      "opened_at": "2026-05-09T04:38:52.232896Z",
      "closed_at": "2026-05-09T04:42:39.381359Z"
    },
    {
      "symbol": "BTCUSDT",
      "side": "buy",
      "entry_price": 80410.9,
      "exit_price": 80394.5,
      "notional_usd": 15,
      "qty": 0.00018654187429813622,
      "pnl_usd": -0.003059286738488348,
      "reason": "max_hold",
      "opened_at": "2026-05-09T04:38:50.012091Z",
      "closed_at": "2026-05-09T04:42:58.404071Z"
    },
    {
      "symbol": "ETHUSDT",
      "side": "buy",
      "entry_price": 2314.55,
      "exit_price": 2314.45,
      "notional_usd": 15,
      "qty": 0.006480741396815795,
      "pnl_usd": -0.0006480741396839373,
      "reason": "max_hold",
      "opened_at": "2026-05-09T04:42:41.869304Z",
      "closed_at": "2026-05-09T04:46:26.402609Z"
    },
    {
      "symbol": "BTCUSDT",
      "side": "buy",
      "entry_price": 80394.5,
      "exit_price": 80411,
      "notional_usd": 15,
      "qty": 0.00018657992773137466,
      "pnl_usd": 0.003078568807567682,
      "reason": "max_hold",
      "opened_at": "2026-05-09T04:43:00.275893Z",
      "closed_at": "2026-05-09T04:46:43.584591Z"
    },
    {
      "symbol": "BTCUSDT",
      "side": "buy",
      "entry_price": 80411,
      "exit_price": 80418.4,
      "notional_usd": 15,
      "qty": 0.00018654164231261892,
      "pnl_usd": 0.0013804081531122942,
      "reason": "max_hold",
      "opened_at": "2026-05-09T04:46:45.844113Z",
      "closed_at": "2026-05-09T04:50:39.327755Z"
    },
    {
      "symbol": "ETHUSDT",
      "side": "buy",
      "entry_price": 2314.45,
      "exit_price": 2313.9,
      "notional_usd": 15,
      "qty": 0.006481021408974055,
      "pnl_usd": -0.003564561774933962,
      "reason": "max_hold",
      "opened_at": "2026-05-09T04:46:28.923842Z",
      "closed_at": "2026-05-09T04:50:42.357114Z"
    },
    {
      "symbol": "BTCUSDT",
      "side": "buy",
      "entry_price": 80418.4,
      "exit_price": 80329.2,
      "notional_usd": 15,
      "qty": 0.00018652447698536655,
      "pnl_usd": -0.016637983347094154,
      "reason": "max_hold",
      "opened_at": "2026-05-09T04:50:42.156686Z",
      "closed_at": "2026-05-09T05:05:20.303228Z"
    },
    {
      "symbol": "ETHUSDT",
      "side": "buy",
      "entry_price": 2313.9,
      "exit_price": 2312.09,
      "notional_usd": 15,
      "qty": 0.006482561908466225,
      "pnl_usd": -0.011733437054323514,
      "reason": "max_hold",
      "opened_at": "2026-05-09T04:50:44.214017Z",
      "closed_at": "2026-05-09T05:05:23.271484Z"
    },
    {
      "symbol": "BTCUSDT",
      "side": "buy",
      "entry_price": 80329.2,
      "exit_price": 80358.8,
      "notional_usd": 15,
      "qty": 0.0001867315994681884,
      "pnl_usd": 0.005527255344259464,
      "reason": "max_hold",
      "opened_at": "2026-05-09T05:05:23.070142Z",
      "closed_at": "2026-05-09T05:12:46.83729Z"
    },
    {
      "symbol": "ETHUSDT",
      "side": "buy",
      "entry_price": 2312.09,
      "exit_price": 2313.52,
      "notional_usd": 15,
      "qty": 0.00648763672694402,
      "pnl_usd": 0.009277320519528887,
      "reason": "max_hold",
      "opened_at": "2026-05-09T05:05:25.137945Z",
      "closed_at": "2026-05-09T05:12:49.61369Z"
    },
    {
      "symbol": "BTCUSDT",
      "side": "buy",
      "entry_price": 80358.8,
      "exit_price": 80403,
      "notional_usd": 15,
      "qty": 0.0001866628172645684,
      "pnl_usd": 0.008250496523093379,
      "reason": "max_hold",
      "opened_at": "2026-05-09T05:12:49.415898Z",
      "closed_at": "2026-05-09T05:24:32.723382Z"
    },
    {
      "symbol": "ETHUSDT",
      "side": "buy",
      "entry_price": 2313.52,
      "exit_price": 2316.31,
      "notional_usd": 15,
      "qty": 0.006483626681420519,
      "pnl_usd": 0.018089318441163012,
      "reason": "max_hold",
      "opened_at": "2026-05-09T05:12:51.452103Z",
      "closed_at": "2026-05-09T05:24:35.56983Z"
    },
    {
      "symbol": "BTCUSDT",
      "side": "buy",
      "entry_price": 80403,
      "exit_price": 80446.7,
      "notional_usd": 15,
      "qty": 0.00018656020297750083,
      "pnl_usd": 0.008152680870116244,
      "reason": "max_hold",
      "opened_at": "2026-05-09T05:24:35.365768Z",
      "closed_at": "2026-05-09T05:43:49.677719Z"
    },
    {
      "symbol": "ETHUSDT",
      "side": "buy",
      "entry_price": 2316.31,
      "exit_price": 2316.33,
      "notional_usd": 15,
      "qty": 0.006475817140192807,
      "pnl_usd": 0.00012951634280373834,
      "reason": "max_hold",
      "opened_at": "2026-05-09T05:24:37.450131Z",
      "closed_at": "2026-05-09T05:43:52.646322Z"
    },
    {
      "symbol": "BTCUSDT",
      "side": "buy",
      "entry_price": 80446.7,
      "exit_price": 80388.1,
      "notional_usd": 15,
      "qty": 0.00018645886033858444,
      "pnl_usd": -0.01092648921583942,
      "reason": "max_hold",
      "opened_at": "2026-05-09T05:43:52.436666Z",
      "closed_at": "2026-05-09T06:09:10.047855Z"
    },
    {
      "symbol": "ETHUSDT",
      "side": "buy",
      "entry_price": 2316.33,
      "exit_price": 2317.52,
      "notional_usd": 15,
      "qty": 0.006475761225732085,
      "pnl_usd": 0.007706155858621534,
      "reason": "max_hold",
      "opened_at": "2026-05-09T05:43:54.505781Z",
      "closed_at": "2026-05-09T06:09:12.963608Z"
    },
    {
      "symbol": "BTCUSDT",
      "side": "buy",
      "entry_price": 80388.1,
      "exit_price": 80270.9,
      "notional_usd": 15,
      "qty": 0.00018659478206351437,
      "pnl_usd": -0.021868908457846056,
      "reason": "max_hold",
      "opened_at": "2026-05-09T06:09:12.769266Z",
      "closed_at": "2026-05-09T06:32:10.652081Z"
    },
    {
      "symbol": "ETHUSDT",
      "side": "buy",
      "entry_price": 2317.52,
      "exit_price": 2316.14,
      "notional_usd": 15,
      "qty": 0.006472436052331803,
      "pnl_usd": -0.008931961752218593,
      "reason": "max_hold",
      "opened_at": "2026-05-09T06:09:14.905366Z",
      "closed_at": "2026-05-09T06:32:13.814182Z"
    },
    {
      "symbol": "BTCUSDT",
      "side": "buy",
      "entry_price": 80270.9,
      "exit_price": 80305.2,
      "notional_usd": 15,
      "qty": 0.00018686722087331775,
      "pnl_usd": 0.006409545675955343,
      "reason": "max_hold",
      "opened_at": "2026-05-09T06:32:13.611322Z",
      "closed_at": "2026-05-09T06:35:19.941305Z"
    },
    {
      "symbol": "ETHUSDT",
      "side": "buy",
      "entry_price": 2316.14,
      "exit_price": 2317.33,
      "notional_usd": 15,
      "qty": 0.006476292452097024,
      "pnl_usd": 0.0077067880179958114,
      "reason": "max_hold",
      "opened_at": "2026-05-09T06:32:15.654775Z",
      "closed_at": "2026-05-09T06:35:21.99204Z"
    },
    {
      "symbol": "BTCUSDT",
      "side": "buy",
      "entry_price": 80305.2,
      "exit_price": 80191.3,
      "notional_usd": 15,
      "qty": 0.00018678740604593478,
      "pnl_usd": -0.021275085548630883,
      "reason": "max_hold",
      "opened_at": "2026-05-09T06:35:21.793628Z",
      "closed_at": "2026-05-09T06:40:29.092988Z"
    },
    {
      "symbol": "ETHUSDT",
      "side": "buy",
      "entry_price": 2317.33,
      "exit_price": 2313.92,
      "notional_usd": 15,
      "qty": 0.006472966733266302,
      "pnl_usd": -0.022072816560437147,
      "reason": "max_hold",
      "opened_at": "2026-05-09T06:35:23.846213Z",
      "closed_at": "2026-05-09T06:40:31.984553Z"
    },
    {
      "symbol": "BTCUSDT",
      "side": "buy",
      "entry_price": 80191.3,
      "exit_price": 80183.9,
      "notional_usd": 15,
      "qty": 0.00018705271020671817,
      "pnl_usd": -0.0013841900555313475,
      "reason": "max_hold",
      "opened_at": "2026-05-09T06:40:31.79217Z",
      "closed_at": "2026-05-09T06:45:53.150297Z"
    },
    {
      "symbol": "ETHUSDT",
      "side": "buy",
      "entry_price": 2313.92,
      "exit_price": 2313.8,
      "notional_usd": 15,
      "qty": 0.006482505877471996,
      "pnl_usd": -0.000777900705295932,
      "reason": "max_hold",
      "opened_at": "2026-05-09T06:40:34.539101Z",
      "closed_at": "2026-05-09T06:45:55.942331Z"
    },
    {
      "symbol": "BTCUSDT",
      "side": "buy",
      "entry_price": 80183.9,
      "exit_price": 80123,
      "notional_usd": 15,
      "qty": 0.0001870699728997966,
      "pnl_usd": -0.011392561349596524,
      "reason": "max_hold",
      "opened_at": "2026-05-09T06:45:55.744985Z",
      "closed_at": "2026-05-09T07:10:55.598778Z"
    },
    {
      "symbol": "ETHUSDT",
      "side": "buy",
      "entry_price": 2313.8,
      "exit_price": 2311.4,
      "notional_usd": 15,
      "qty": 0.00648284207796698,
      "pnl_usd": -0.015558820987121342,
      "reason": "max_hold",
      "opened_at": "2026-05-09T06:45:57.827566Z",
      "closed_at": "2026-05-09T07:11:21.344442Z"
    },
    {
      "symbol": "BTCUSDT",
      "side": "buy",
      "entry_price": 80123,
      "exit_price": 80151.4,
      "notional_usd": 15,
      "qty": 0.00018721216130199818,
      "pnl_usd": 0.005316825380975659,
      "reason": "max_hold",
      "opened_at": "2026-05-09T07:11:01.240204Z",
      "closed_at": "2026-05-09T07:15:31.375087Z"
    },
    {
      "symbol": "ETHUSDT",
      "side": "buy",
      "entry_price": 2311.4,
      "exit_price": 2312.16,
      "notional_usd": 15,
      "qty": 0.0064895734187072765,
      "pnl_usd": 0.004932075798215995,
      "reason": "max_hold",
      "opened_at": "2026-05-09T07:11:25.708478Z",
      "closed_at": "2026-05-09T07:15:34.495735Z"
    },
    {
      "symbol": "BTCUSDT",
      "side": "buy",
      "entry_price": 80151.4,
      "exit_price": 80194.5,
      "notional_usd": 15,
      "qty": 0.00018714582652330466,
      "pnl_usd": 0.00806598512315552,
      "reason": "max_hold",
      "opened_at": "2026-05-09T07:15:34.27686Z",
      "closed_at": "2026-05-09T07:20:10.024497Z"
    },
    {
      "symbol": "ETHUSDT",
      "side": "buy",
      "entry_price": 2312.16,
      "exit_price": 2315.25,
      "notional_usd": 15,
      "qty": 0.006487440315549097,
      "pnl_usd": 0.020046190575047654,
      "reason": "max_hold",
      "opened_at": "2026-05-09T07:15:36.582864Z",
      "closed_at": "2026-05-09T07:20:18.003688Z"
    },
    {
      "symbol": "BTCUSDT",
      "side": "buy",
      "entry_price": 80192.9,
      "exit_price": 80226.8,
      "notional_usd": 15,
      "qty": 0.00018704897815143237,
      "pnl_usd": 0.006340960359335191,
      "reason": "max_hold",
      "opened_at": "2026-05-09T07:20:13.825006Z",
      "closed_at": "2026-05-09T07:24:27.14876Z"
    },
    {
      "symbol": "ETHUSDT",
      "side": "buy",
      "entry_price": 2315.25,
      "exit_price": 2315.62,
      "notional_usd": 15,
      "qty": 0.00647878198898607,
      "pnl_usd": 0.002397149335924139,
      "reason": "max_hold",
      "opened_at": "2026-05-09T07:20:19.878452Z",
      "closed_at": "2026-05-09T07:24:30.084047Z"
    },
    {
      "symbol": "BTCUSDT",
      "side": "buy",
      "entry_price": 80226.8,
      "exit_price": 80185.8,
      "notional_usd": 15,
      "qty": 0.0001869699402194778,
      "pnl_usd": -0.007665767548998589,
      "reason": "max_hold",
      "opened_at": "2026-05-09T07:24:29.883438Z",
      "closed_at": "2026-05-09T07:42:04.607114Z"
    },
    {
      "symbol": "ETHUSDT",
      "side": "buy",
      "entry_price": 2315.62,
      "exit_price": 2314.67,
      "notional_usd": 15,
      "qty": 0.006477746780559851,
      "pnl_usd": -0.0061538594415306794,
      "reason": "max_hold",
      "opened_at": "2026-05-09T07:24:31.990473Z",
      "closed_at": "2026-05-09T07:42:08.201908Z"
    },
    {
      "symbol": "BTCUSDT",
      "side": "buy",
      "entry_price": 80185.8,
      "exit_price": 80192.5,
      "notional_usd": 15,
      "qty": 0.00018706554028269343,
      "pnl_usd": 0.0012533391198935016,
      "reason": "max_hold",
      "opened_at": "2026-05-09T07:42:07.998625Z",
      "closed_at": "2026-05-09T07:45:19.80966Z"
    },
    {
      "symbol": "ETHUSDT",
      "side": "buy",
      "entry_price": 2314.67,
      "exit_price": 2314.35,
      "notional_usd": 15,
      "qty": 0.00648040541416271,
      "pnl_usd": -0.002073729732533128,
      "reason": "max_hold",
      "opened_at": "2026-05-09T07:42:10.610871Z",
      "closed_at": "2026-05-09T07:45:27.653796Z"
    },
    {
      "symbol": "BTCUSDT",
      "side": "buy",
      "entry_price": 80192.5,
      "exit_price": 80179.5,
      "notional_usd": 15,
      "qty": 0.0001870499111512922,
      "pnl_usd": -0.0024316488449667986,
      "reason": "max_hold",
      "opened_at": "2026-05-09T07:45:22.427764Z",
      "closed_at": "2026-05-09T07:52:53.862292Z"
    },
    {
      "symbol": "ETHUSDT",
      "side": "buy",
      "entry_price": 2314.35,
      "exit_price": 2314.65,
      "notional_usd": 15,
      "qty": 0.006481301445330222,
      "pnl_usd": 0.0019443904336002456,
      "reason": "max_hold",
      "opened_at": "2026-05-09T07:45:29.563573Z",
      "closed_at": "2026-05-09T07:53:00.901796Z"
    },
    {
      "symbol": "BTCUSDT",
      "side": "buy",
      "entry_price": 80179.8,
      "exit_price": 80373.9,
      "notional_usd": 15,
      "qty": 0.00018707953873668928,
      "pnl_usd": 0.03631213846878976,
      "reason": "max_hold",
      "opened_at": "2026-05-09T07:52:57.732858Z",
      "closed_at": "2026-05-09T08:16:33.899343Z"
    },
    {
      "symbol": "ETHUSDT",
      "side": "buy",
      "entry_price": 2314.65,
      "exit_price": 2318.1,
      "notional_usd": 15,
      "qty": 0.00648046140885231,
      "pnl_usd": 0.022357591860539292,
      "reason": "max_hold",
      "opened_at": "2026-05-09T07:53:02.904078Z",
      "closed_at": "2026-05-09T08:16:37.479521Z"
    },
    {
      "symbol": "ETHUSDT",
      "side": "buy",
      "entry_price": 2318.1,
      "exit_price": 2318.15,
      "notional_usd": 15,
      "qty": 0.006470816617057073,
      "pnl_usd": 0.0003235408308540307,
      "reason": "max_hold",
      "opened_at": "2026-05-09T08:16:39.389792Z",
      "closed_at": "2026-05-09T08:19:54.145977Z"
    },
    {
      "symbol": "BTCUSDT",
      "side": "buy",
      "entry_price": 80373.9,
      "exit_price": 80344.5,
      "notional_usd": 15,
      "qty": 0.00018662774856016692,
      "pnl_usd": -0.005486855807667821,
      "reason": "max_hold",
      "opened_at": "2026-05-09T08:16:37.136775Z",
      "closed_at": "2026-05-09T08:25:32.95033Z"
    },
    {
      "symbol": "ETHUSDT",
      "side": "buy",
      "entry_price": 2318.15,
      "exit_price": 2317.65,
      "notional_usd": 15,
      "qty": 0.006470677048508509,
      "pnl_usd": -0.0032353385242542545,
      "reason": "max_hold",
      "opened_at": "2026-05-09T08:19:56.038543Z",
      "closed_at": "2026-05-09T08:25:41.023081Z"
    },
    {
      "symbol": "BTCUSDT",
      "side": "buy",
      "entry_price": 80342.4,
      "exit_price": 80363.1,
      "notional_usd": 15,
      "qty": 0.00018670092006213408,
      "pnl_usd": 0.003864709045288349,
      "reason": "max_hold",
      "opened_at": "2026-05-09T08:25:36.953753Z",
      "closed_at": "2026-05-09T08:29:03.525545Z"
    },
    {
      "symbol": "ETHUSDT",
      "side": "buy",
      "entry_price": 2317.65,
      "exit_price": 2318.01,
      "notional_usd": 15,
      "qty": 0.006472073004983496,
      "pnl_usd": 0.002329946281794883,
      "reason": "max_hold",
      "opened_at": "2026-05-09T08:25:42.931193Z",
      "closed_at": "2026-05-09T08:29:07.054612Z"
    },
    {
      "symbol": "BTCUSDT",
      "side": "buy",
      "entry_price": 80363.1,
      "exit_price": 80396.7,
      "notional_usd": 15,
      "qty": 0.00018665282947024194,
      "pnl_usd": 0.0062715350701985,
      "reason": "max_hold",
      "opened_at": "2026-05-09T08:29:06.847416Z",
      "closed_at": "2026-05-09T08:34:24.856942Z"
    },
    {
      "symbol": "ETHUSDT",
      "side": "buy",
      "entry_price": 2318.01,
      "exit_price": 2318.21,
      "notional_usd": 15,
      "qty": 0.006471067855617533,
      "pnl_usd": 0.0012942135711223296,
      "reason": "max_hold",
      "opened_at": "2026-05-09T08:29:09.671548Z",
      "closed_at": "2026-05-09T08:34:27.822149Z"
    },
    {
      "symbol": "ETHUSDT",
      "side": "buy",
      "entry_price": 2318.21,
      "exit_price": 2318.25,
      "notional_usd": 15,
      "qty": 0.006470509574197333,
      "pnl_usd": 0.0002588203829676579,
      "reason": "max_hold",
      "opened_at": "2026-05-09T08:34:29.728093Z",
      "closed_at": "2026-05-09T08:38:00.09157Z"
    },
    {
      "symbol": "BTCUSDT",
      "side": "buy",
      "entry_price": 80396.7,
      "exit_price": 80415.5,
      "notional_usd": 15,
      "qty": 0.00018657482210090713,
      "pnl_usd": 0.003507606655497597,
      "reason": "max_hold",
      "opened_at": "2026-05-09T08:34:27.610921Z",
      "closed_at": "2026-05-09T08:38:18.107292Z"
    },
    {
      "symbol": "BTCUSDT",
      "side": "buy",
      "entry_price": 80415.5,
      "exit_price": 80386.1,
      "notional_usd": 15,
      "qty": 0.00018653120356150246,
      "pnl_usd": -0.005484017384707086,
      "reason": "max_hold",
      "opened_at": "2026-05-09T08:38:20.394723Z",
      "closed_at": "2026-05-09T08:41:34.64731Z"
    },
    {
      "symbol": "ETHUSDT",
      "side": "buy",
      "entry_price": 2318.25,
      "exit_price": 2316.81,
      "notional_usd": 15,
      "qty": 0.006470397929472662,
      "pnl_usd": -0.009317373018440987,
      "reason": "max_hold",
      "opened_at": "2026-05-09T08:38:02.444059Z",
      "closed_at": "2026-05-09T08:41:59.281144Z"
    },
    {
      "symbol": "BTCUSDT",
      "side": "buy",
      "entry_price": 80386.1,
      "exit_price": 80379.3,
      "notional_usd": 15,
      "qty": 0.00018659942452737475,
      "pnl_usd": -0.0012688760867866915,
      "reason": "max_hold",
      "opened_at": "2026-05-09T08:41:37.246851Z",
      "closed_at": "2026-05-09T08:50:14.827212Z"
    },
    {
      "symbol": "ETHUSDT",
      "side": "buy",
      "entry_price": 2316.81,
      "exit_price": 2315.45,
      "notional_usd": 15,
      "qty": 0.006474419568285704,
      "pnl_usd": -0.008805210612869381,
      "reason": "max_hold",
      "opened_at": "2026-05-09T08:42:01.191998Z",
      "closed_at": "2026-05-09T08:50:17.75895Z"
    },
    {
      "symbol": "BTCUSDT",
      "side": "buy",
      "entry_price": 80379.3,
      "exit_price": 80377.2,
      "notional_usd": 15,
      "qty": 0.00018661521063258822,
      "pnl_usd": -0.0003918919423295215,
      "reason": "max_hold",
      "opened_at": "2026-05-09T08:50:17.558919Z",
      "closed_at": "2026-05-09T09:01:54.987098Z"
    },
    {
      "symbol": "BTCUSDT",
      "side": "buy",
      "entry_price": 80377.2,
      "exit_price": 80340.1,
      "notional_usd": 15,
      "qty": 0.00018662008629312792,
      "pnl_usd": -0.006923605201473416,
      "reason": "max_hold",
      "opened_at": "2026-05-09T09:01:57.997194Z",
      "closed_at": "2026-05-09T09:11:50.897407Z"
    },
    {
      "symbol": "ETHUSDT",
      "side": "buy",
      "entry_price": 2315.45,
      "exit_price": 2314.81,
      "notional_usd": 15,
      "qty": 0.006478222375780086,
      "pnl_usd": -0.004146062320498431,
      "reason": "max_hold",
      "opened_at": "2026-05-09T09:01:36.759739Z",
      "closed_at": "2026-05-09T09:11:54.222494Z"
    },
    {
      "symbol": "BTCUSDT",
      "side": "buy",
      "entry_price": 80340.1,
      "exit_price": 80248.8,
      "notional_usd": 15,
      "qty": 0.00018670626499095718,
      "pnl_usd": -0.017046281993674934,
      "reason": "max_hold",
      "opened_at": "2026-05-09T09:11:54.021566Z",
      "closed_at": "2026-05-09T09:23:17.994966Z"
    },
    {
      "symbol": "ETHUSDT",
      "side": "buy",
      "entry_price": 2314.81,
      "exit_price": 2312.69,
      "notional_usd": 15,
      "qty": 0.006480013478428036,
      "pnl_usd": -0.013737628574266728,
      "reason": "max_hold",
      "opened_at": "2026-05-09T09:11:56.522382Z",
      "closed_at": "2026-05-09T09:23:21.500852Z"
    },
    {
      "symbol": "BTCUSDT",
      "side": "buy",
      "entry_price": 80248.8,
      "exit_price": 80211.9,
      "notional_usd": 15,
      "qty": 0.00018691868289619283,
      "pnl_usd": -0.006897299398871147,
      "reason": "max_hold",
      "opened_at": "2026-05-09T09:23:21.2924Z",
      "closed_at": "2026-05-09T09:42:57.896261Z"
    },
    {
      "symbol": "ETHUSDT",
      "side": "buy",
      "entry_price": 2312.69,
      "exit_price": 2313.34,
      "notional_usd": 15,
      "qty": 0.006485953586516135,
      "pnl_usd": 0.004215869831236078,
      "reason": "max_hold",
      "opened_at": "2026-05-09T09:23:23.415034Z",
      "closed_at": "2026-05-09T09:43:00.870589Z"
    },
    {
      "symbol": "BTCUSDT",
      "side": "buy",
      "entry_price": 80211.9,
      "exit_price": 80184.2,
      "notional_usd": 15,
      "qty": 0.000187004671376691,
      "pnl_usd": -0.005180029397133796,
      "reason": "max_hold",
      "opened_at": "2026-05-09T09:43:00.666076Z",
      "closed_at": "2026-05-09T10:14:17.746873Z"
    },
    {
      "symbol": "ETHUSDT",
      "side": "buy",
      "entry_price": 2313.34,
      "exit_price": 2311.76,
      "notional_usd": 15,
      "qty": 0.006484131169650808,
      "pnl_usd": -0.010244927248047805,
      "reason": "max_hold",
      "opened_at": "2026-05-09T09:43:02.764274Z",
      "closed_at": "2026-05-09T10:14:20.453847Z"
    },
    {
      "symbol": "BTCUSDT",
      "side": "buy",
      "entry_price": 80184.2,
      "exit_price": 80204.6,
      "notional_usd": 15,
      "qty": 0.00018706927299891999,
      "pnl_usd": 0.003816213169179601,
      "reason": "max_hold",
      "opened_at": "2026-05-09T10:14:20.250466Z",
      "closed_at": "2026-05-09T10:17:59.32992Z"
    },
    {
      "symbol": "ETHUSDT",
      "side": "buy",
      "entry_price": 2311.76,
      "exit_price": 2312.51,
      "notional_usd": 15,
      "qty": 0.006488562826590995,
      "pnl_usd": 0.004866422119943247,
      "reason": "max_hold",
      "opened_at": "2026-05-09T10:14:22.386349Z",
      "closed_at": "2026-05-09T10:18:02.250448Z"
    },
    {
      "symbol": "BTCUSDT",
      "side": "buy",
      "entry_price": 80204.6,
      "exit_price": 80170.5,
      "notional_usd": 15,
      "qty": 0.00018702169202265204,
      "pnl_usd": -0.006377439697973523,
      "reason": "max_hold",
      "opened_at": "2026-05-09T10:18:02.049525Z",
      "closed_at": "2026-05-09T10:21:33.968192Z"
    },
    {
      "symbol": "ETHUSDT",
      "side": "buy",
      "entry_price": 2312.51,
      "exit_price": 2310.85,
      "notional_usd": 15,
      "qty": 0.006486458436936488,
      "pnl_usd": -0.010767521005316576,
      "reason": "max_hold",
      "opened_at": "2026-05-09T10:18:04.154784Z",
      "closed_at": "2026-05-09T10:23:57.448152Z"
    },
    {
      "symbol": "BTCUSDT",
      "side": "buy",
      "entry_price": 80170.5,
      "exit_price": 80164.6,
      "notional_usd": 15,
      "qty": 0.00018710124048122438,
      "pnl_usd": -0.0011038973188381349,
      "reason": "max_hold",
      "opened_at": "2026-05-09T10:21:36.356499Z",
      "closed_at": "2026-05-09T10:24:53.516721Z"
    },
    {
      "symbol": "ETHUSDT",
      "side": "buy",
      "entry_price": 2310.85,
      "exit_price": 2311.15,
      "notional_usd": 15,
      "qty": 0.006491117986887942,
      "pnl_usd": 0.0019473353960675634,
      "reason": "max_hold",
      "opened_at": "2026-05-09T10:23:59.407073Z",
      "closed_at": "2026-05-09T10:27:11.77401Z"
    },
    {
      "symbol": "BTCUSDT",
      "side": "buy",
      "entry_price": 80164.6,
      "exit_price": 80205.5,
      "notional_usd": 15,
      "qty": 0.00018711501086514495,
      "pnl_usd": 0.007653003944383339,
      "reason": "max_hold",
      "opened_at": "2026-05-09T10:24:55.518697Z",
      "closed_at": "2026-05-09T10:28:44.086768Z"
    },
    {
      "symbol": "ETHUSDT",
      "side": "buy",
      "entry_price": 2311.15,
      "exit_price": 2310.96,
      "notional_usd": 15,
      "qty": 0.0064902754040196435,
      "pnl_usd": -0.0012331523267640864,
      "reason": "max_hold",
      "opened_at": "2026-05-09T10:27:13.672981Z",
      "closed_at": "2026-05-09T10:30:30.932767Z"
    },
    {
      "symbol": "BTCUSDT",
      "side": "buy",
      "entry_price": 80205.5,
      "exit_price": 80200.5,
      "notional_usd": 15,
      "qty": 0.0001870195934194039,
      "pnl_usd": -0.0009350979670970196,
      "reason": "max_hold",
      "opened_at": "2026-05-09T10:28:46.556083Z",
      "closed_at": "2026-05-09T10:32:32.263601Z"
    },
    {
      "symbol": "ETHUSDT",
      "side": "buy",
      "entry_price": 2310.96,
      "exit_price": 2311.99,
      "notional_usd": 15,
      "qty": 0.006490809014435559,
      "pnl_usd": 0.0066855332848669725,
      "reason": "max_hold",
      "opened_at": "2026-05-09T10:30:32.832734Z",
      "closed_at": "2026-05-09T10:33:37.291512Z"
    },
    {
      "symbol": "BTCUSDT",
      "side": "buy",
      "entry_price": 80200.5,
      "exit_price": 80233.5,
      "notional_usd": 15,
      "qty": 0.00018703125292236333,
      "pnl_usd": 0.00617203134643799,
      "reason": "max_hold",
      "opened_at": "2026-05-09T10:32:35.458142Z",
      "closed_at": "2026-05-09T10:35:52.388704Z"
    },
    {
      "symbol": "ETHUSDT",
      "side": "buy",
      "entry_price": 2311.99,
      "exit_price": 2312.57,
      "notional_usd": 15,
      "qty": 0.006487917335282593,
      "pnl_usd": 0.003762992054466382,
      "reason": "max_hold",
      "opened_at": "2026-05-09T10:33:39.260371Z",
      "closed_at": "2026-05-09T10:36:54.284814Z"
    },
    {
      "symbol": "BTCUSDT",
      "side": "buy",
      "entry_price": 80233.5,
      "exit_price": 80244.9,
      "notional_usd": 15,
      "qty": 0.00018695432705789975,
      "pnl_usd": 0.002131279328458969,
      "reason": "max_hold",
      "opened_at": "2026-05-09T10:35:54.301868Z",
      "closed_at": "2026-05-09T10:39:15.952599Z"
    },
    {
      "symbol": "ETHUSDT",
      "side": "buy",
      "entry_price": 2312.57,
      "exit_price": 2314.34,
      "notional_usd": 15,
      "qty": 0.006486290144730754,
      "pnl_usd": 0.011480733556173316,
      "reason": "max_hold",
      "opened_at": "2026-05-09T10:36:56.208848Z",
      "closed_at": "2026-05-09T10:40:18.057629Z"
    },
    {
      "symbol": "BTCUSDT",
      "side": "buy",
      "entry_price": 80244.9,
      "exit_price": 80303.2,
      "notional_usd": 15,
      "qty": 0.00018692776737213207,
      "pnl_usd": 0.010897888837795845,
      "reason": "max_hold",
      "opened_at": "2026-05-09T10:39:18.1626Z",
      "closed_at": "2026-05-09T10:43:49.047678Z"
    },
    {
      "symbol": "ETHUSDT",
      "side": "buy",
      "entry_price": 2314.34,
      "exit_price": 2313.6,
      "notional_usd": 15,
      "qty": 0.006481329450296844,
      "pnl_usd": -0.004796183793221197,
      "reason": "max_hold",
      "opened_at": "2026-05-09T10:40:19.951522Z",
      "closed_at": "2026-05-09T10:43:51.766396Z"
    },
    {
      "symbol": "BTCUSDT",
      "side": "buy",
      "entry_price": 80303.2,
      "exit_price": 80282,
      "notional_usd": 15,
      "qty": 0.00018679205809980177,
      "pnl_usd": -0.003959991631715253,
      "reason": "max_hold",
      "opened_at": "2026-05-09T10:43:51.555774Z",
      "closed_at": "2026-05-09T10:47:20.40285Z"
    },
    {
      "symbol": "ETHUSDT",
      "side": "buy",
      "entry_price": 2313.6,
      "exit_price": 2312.93,
      "notional_usd": 15,
      "qty": 0.006483402489626556,
      "pnl_usd": -0.0043438796680502646,
      "reason": "max_hold",
      "opened_at": "2026-05-09T10:43:53.67595Z",
      "closed_at": "2026-05-09T10:47:22.763394Z"
    },
    {
      "symbol": "BTCUSDT",
      "side": "buy",
      "entry_price": 80282,
      "exit_price": 80235.1,
      "notional_usd": 15,
      "qty": 0.00018684138412097356,
      "pnl_usd": -0.008762860915272572,
      "reason": "max_hold",
      "opened_at": "2026-05-09T10:47:22.553604Z",
      "closed_at": "2026-05-09T10:50:50.409762Z"
    },
    {
      "symbol": "ETHUSDT",
      "side": "buy",
      "entry_price": 2312.93,
      "exit_price": 2311.69,
      "notional_usd": 15,
      "qty": 0.0064852805748552705,
      "pnl_usd": -0.008041747912819119,
      "reason": "max_hold",
      "opened_at": "2026-05-09T10:47:24.761825Z",
      "closed_at": "2026-05-09T10:50:53.115646Z"
    },
    {
      "symbol": "BTCUSDT",
      "side": "buy",
      "entry_price": 80235.1,
      "exit_price": 80244.1,
      "notional_usd": 15,
      "qty": 0.00018695059892740208,
      "pnl_usd": 0.0016825553903466186,
      "reason": "max_hold",
      "opened_at": "2026-05-09T10:50:52.905069Z",
      "closed_at": "2026-05-09T10:54:20.393664Z"
    },
    {
      "symbol": "ETHUSDT",
      "side": "buy",
      "entry_price": 2311.69,
      "exit_price": 2311.91,
      "notional_usd": 15,
      "qty": 0.006488759305962304,
      "pnl_usd": 0.0014275270473104087,
      "reason": "max_hold",
      "opened_at": "2026-05-09T10:50:55.207699Z",
      "closed_at": "2026-05-09T10:54:22.62258Z"
    },
    {
      "symbol": "BTCUSDT",
      "side": "buy",
      "entry_price": 80244.1,
      "exit_price": 80235,
      "notional_usd": 15,
      "qty": 0.00018692963096352254,
      "pnl_usd": -0.0017010596417691432,
      "reason": "max_hold",
      "opened_at": "2026-05-09T10:54:22.372243Z",
      "closed_at": "2026-05-09T10:57:50.423397Z"
    },
    {
      "symbol": "ETHUSDT",
      "side": "buy",
      "entry_price": 2311.91,
      "exit_price": 2311.69,
      "notional_usd": 15,
      "qty": 0.006488141839431466,
      "pnl_usd": -0.0014273912046736245,
      "reason": "max_hold",
      "opened_at": "2026-05-09T10:54:24.622428Z",
      "closed_at": "2026-05-09T10:57:52.859551Z"
    },
    {
      "symbol": "BTCUSDT",
      "side": "buy",
      "entry_price": 80235,
      "exit_price": 80213.5,
      "notional_usd": 15,
      "qty": 0.0001869508319312021,
      "pnl_usd": -0.004019442886520845,
      "reason": "max_hold",
      "opened_at": "2026-05-09T10:57:52.584195Z",
      "closed_at": "2026-05-09T11:00:55.356825Z"
    },
    {
      "symbol": "ETHUSDT",
      "side": "buy",
      "entry_price": 2311.69,
      "exit_price": 2311.85,
      "notional_usd": 15,
      "qty": 0.006488759305962304,
      "pnl_usd": 0.0010382014889530244,
      "reason": "max_hold",
      "opened_at": "2026-05-09T10:57:54.733199Z",
      "closed_at": "2026-05-09T11:01:01.806601Z"
    },
    {
      "symbol": "BTCUSDT",
      "side": "buy",
      "entry_price": 80213.5,
      "exit_price": 80260.6,
      "notional_usd": 15,
      "qty": 0.0001870009412380709,
      "pnl_usd": 0.008807744332314228,
      "reason": "max_hold",
      "opened_at": "2026-05-09T11:00:56.637964Z",
      "closed_at": "2026-05-09T11:04:20.359107Z"
    },
    {
      "symbol": "ETHUSDT",
      "side": "buy",
      "entry_price": 2311.85,
      "exit_price": 2312.96,
      "notional_usd": 15,
      "qty": 0.006488310227739689,
      "pnl_usd": 0.00720202435279188,
      "reason": "max_hold",
      "opened_at": "2026-05-09T11:01:03.211094Z",
      "closed_at": "2026-05-09T11:04:21.665761Z"
    },
    {
      "symbol": "BTCUSDT",
      "side": "buy",
      "entry_price": 80260.6,
      "exit_price": 80243.3,
      "notional_usd": 15,
      "qty": 0.0001868912019097789,
      "pnl_usd": -0.0032332177930397186,
      "reason": "max_hold",
      "opened_at": "2026-05-09T11:04:21.496951Z",
      "closed_at": "2026-05-09T11:07:50.649679Z"
    },
    {
      "symbol": "ETHUSDT",
      "side": "buy",
      "entry_price": 2312.96,
      "exit_price": 2312.85,
      "notional_usd": 15,
      "qty": 0.006485196458218041,
      "pnl_usd": -0.0007133716104048103,
      "reason": "max_hold",
      "opened_at": "2026-05-09T11:04:22.802753Z",
      "closed_at": "2026-05-09T11:07:52.019469Z"
    },
    {
      "symbol": "BTCUSDT",
      "side": "buy",
      "entry_price": 80243.3,
      "exit_price": 80281.4,
      "notional_usd": 15,
      "qty": 0.00018693149459207185,
      "pnl_usd": 0.007122089943956305,
      "reason": "max_hold",
      "opened_at": "2026-05-09T11:07:51.848333Z",
      "closed_at": "2026-05-09T11:11:20.431067Z"
    },
    {
      "symbol": "ETHUSDT",
      "side": "buy",
      "entry_price": 2312.85,
      "exit_price": 2313.71,
      "notional_usd": 15,
      "qty": 0.006485504896556197,
      "pnl_usd": 0.005577534211039155,
      "reason": "max_hold",
      "opened_at": "2026-05-09T11:07:53.285715Z",
      "closed_at": "2026-05-09T11:11:22.07759Z"
    },
    {
      "symbol": "BTCUSDT",
      "side": "buy",
      "entry_price": 80281.4,
      "exit_price": 80294.3,
      "notional_usd": 15,
      "qty": 0.0001868427805195226,
      "pnl_usd": 0.0024102718687034727,
      "reason": "max_hold",
      "opened_at": "2026-05-09T11:11:21.613596Z",
      "closed_at": "2026-05-09T11:14:50.663313Z"
    },
    {
      "symbol": "ETHUSDT",
      "side": "buy",
      "entry_price": 2313.71,
      "exit_price": 2313.5,
      "notional_usd": 15,
      "qty": 0.006483094251224225,
      "pnl_usd": -0.001361449792757323,
      "reason": "max_hold",
      "opened_at": "2026-05-09T11:11:23.19111Z",
      "closed_at": "2026-05-09T11:14:52.074112Z"
    },
    {
      "symbol": "BTCUSDT",
      "side": "buy",
      "entry_price": 80294.3,
      "exit_price": 80300.5,
      "notional_usd": 15,
      "qty": 0.00018681276254977003,
      "pnl_usd": 0.0011582391278080306,
      "reason": "max_hold",
      "opened_at": "2026-05-09T11:14:51.843955Z",
      "closed_at": "2026-05-09T11:18:20.392339Z"
    },
    {
      "symbol": "ETHUSDT",
      "side": "buy",
      "entry_price": 2313.5,
      "exit_price": 2313.49,
      "notional_usd": 15,
      "qty": 0.006483682731791658,
      "pnl_usd": -0.00006483682731933183,
      "reason": "max_hold",
      "opened_at": "2026-05-09T11:14:53.206348Z",
      "closed_at": "2026-05-09T11:18:22.089129Z"
    },
    {
      "symbol": "BTCUSDT",
      "side": "buy",
      "entry_price": 80300.5,
      "exit_price": 80337.4,
      "notional_usd": 15,
      "qty": 0.00018679833874010748,
      "pnl_usd": 0.006892858699508879,
      "reason": "max_hold",
      "opened_at": "2026-05-09T11:18:21.630159Z",
      "closed_at": "2026-05-09T11:21:50.460521Z"
    },
    {
      "symbol": "ETHUSDT",
      "side": "buy",
      "entry_price": 2313.49,
      "exit_price": 2313.89,
      "notional_usd": 15,
      "qty": 0.006483710757340642,
      "pnl_usd": 0.0025934843029368462,
      "reason": "max_hold",
      "opened_at": "2026-05-09T11:18:23.363553Z",
      "closed_at": "2026-05-09T11:21:51.808108Z"
    }
  ]
}